{
    "fluentMethods": true,
    "relationships": [],
    "fields": [
        {
            "fieldName": "filingStatus",
            "fieldType": "String"
        },
        {
            "fieldName": "exemptFromWithHolding",
            "fieldType": "Boolean"
        },
        {
            "fieldName": "allowances",
            "fieldType": "Integer"
        },
        {
            "fieldName": "extraWithHolding",
            "fieldType": "Float"
        },
        {
            "fieldName": "employeeCode",
            "fieldType": "String"
        },
        {
            "fieldName": "createdDate",
            "fieldType": "LocalDate"
        },
        {
            "fieldName": "createdBy",
            "fieldType": "String"
        }
    ],
    "changelogDate": "20171223053451",
    "entityTableName": "employee_local_tax",
    "dto": "no",
    "pagination": "no",
    "service": "no",
    "jpaMetamodelFiltering": false
}